raesl/__init__.py
raesl/__main__.py
raesl/cli.py
raesl/pygments.py
raesl/types.py
raesl/utils.py
raesl/canopy/__init__.py
raesl/canopy/html.py
raesl/compile/__init__.py
raesl/compile/cli.py
raesl/compile/diagnostics.py
raesl/compile/esl_lines.py
raesl/compile/parser.py
raesl/compile/scanner.py
raesl/compile/state_machine.py
raesl/compile/ast/__init__.py
raesl/compile/ast/comment_storage.py
raesl/compile/ast/components.py
raesl/compile/ast/exprs.py
raesl/compile/ast/nodes.py
raesl/compile/ast/relations.py
raesl/compile/ast/specification.py
raesl/compile/ast/types.py
raesl/compile/ast/verbs.py
raesl/compile/instantiating/__init__.py
raesl/compile/instantiating/edge_building.py
raesl/compile/instantiating/graph_building.py
raesl/compile/instantiating/graph_data.py
raesl/compile/instantiating/instantation_graph_structure.yml
raesl/compile/instantiating/node_building.py
raesl/compile/machine_files/__init__.py
raesl/compile/machine_files/argument_list.py
raesl/compile/machine_files/behavior.py
raesl/compile/machine_files/builder.py
raesl/compile/machine_files/comments.py
raesl/compile/machine_files/component_definitions.py
raesl/compile/machine_files/component_instances.py
raesl/compile/machine_files/designs.py
raesl/compile/machine_files/goals.py
raesl/compile/machine_files/groups.py
raesl/compile/machine_files/machine_parts.py
raesl/compile/machine_files/needs.py
raesl/compile/machine_files/parameters.py
raesl/compile/machine_files/relation_definitions.py
raesl/compile/machine_files/relation_instances.py
raesl/compile/machine_files/sub_clause.py
raesl/compile/machine_files/transforms.py
raesl/compile/machine_files/type_defs.py
raesl/compile/machine_files/typing.py
raesl/compile/machine_files/utils.py
raesl/compile/machine_files/variables.py
raesl/compile/machine_files/verb_defs.py
raesl/compile/typechecking/__init__.py
raesl/compile/typechecking/ast_builder.py
raesl/compile/typechecking/compdef_behavior_builder.py
raesl/compile/typechecking/compdef_builder.py
raesl-0.16.2.dist-info/METADATA
raesl-0.16.2.dist-info/WHEEL
raesl-0.16.2.dist-info/entry_points.txt
raesl-0.16.2.dist-info/licenses/LICENSE.md
raesl-0.16.2.dist-info/RECORD
