Metadata-Version: 2.4
Name: raesl
Version: 0.16.2
Summary: Ratio ESL support in Python.
Project-URL: Homepage, https://raesl.ratio-case.nl
Project-URL: Repository, https://gitlab.com/ratio-case-os/python/raesl
Project-URL: Bug Tracker, https://gitlab.com/ratio-case-os/python/raesl/-/issues
Project-URL: Changelog, https://raesl.ratio-case.nl/CHANGELOG/
Author-email: "Ratio Innovations B.V." <info@ratio-case.nl>
License-Expression: GPL-3.0-or-later
License-File: LICENSE.md
Keywords: engineering,language,management,requirements,specification,systems
Requires-Python: >=3.11
Requires-Dist: click-log>=0.4.0
Requires-Dist: click>=8.3.1
Requires-Dist: graphviz>=0.21.0
Requires-Dist: openpyxl>=3.1.5
Requires-Dist: plotly[kaleido]>=6.5.0
Requires-Dist: ragraph[plot]>=1.23.2
Requires-Dist: sly>=0.5
Provides-Extra: all
Requires-Dist: ipykernel>=7.1.0; extra == 'all'
Requires-Dist: ipython>=9.4.0; extra == 'all'
Requires-Dist: jupyter-client>=8.6.3; extra == 'all'
Requires-Dist: jupyter-server>=2.17.0; extra == 'all'
Requires-Dist: lsprotocol>=2023.0.1; extra == 'all'
Requires-Dist: pandoc-fignos>=2.4.0; extra == 'all'
Requires-Dist: pluggy>=1.6.0; extra == 'all'
Requires-Dist: pygls>=1.3.1; extra == 'all'
Requires-Dist: pygments>=2.19.2; extra == 'all'
Requires-Dist: pypandoc>=1.15; extra == 'all'
Requires-Dist: pypst>=0.7.0; extra == 'all'
Requires-Dist: ratio-typst>=0.1.4; extra == 'all'
Requires-Dist: typst>=0.14.2; extra == 'all'
Provides-Extra: doc
Requires-Dist: pandoc-fignos>=2.4.0; extra == 'doc'
Requires-Dist: pluggy>=1.6.0; extra == 'doc'
Requires-Dist: pypandoc>=1.15; extra == 'doc'
Provides-Extra: jupyter
Requires-Dist: ipykernel>=7.1.0; extra == 'jupyter'
Requires-Dist: ipython>=9.4.0; extra == 'jupyter'
Requires-Dist: jupyter-client>=8.6.3; extra == 'jupyter'
Requires-Dist: jupyter-server>=2.16.0; extra == 'jupyter'
Provides-Extra: pygments
Requires-Dist: pygments>=2.19.2; extra == 'pygments'
Provides-Extra: render
Requires-Dist: pypst>=0.7.0; extra == 'render'
Requires-Dist: ratio-typst>=0.1.4; extra == 'render'
Requires-Dist: typst>=0.14.2; extra == 'render'
Provides-Extra: server
Requires-Dist: lsprotocol>=2023.0.1; extra == 'server'
Requires-Dist: pygls>=1.3.1; extra == 'server'
